{
  "items": [
    {
      "sys": {
        "id": "1"
      },
      "fields": {
        "title": "MSI TWIN FROZER",
        "price": 329.99,
        "image": {
          "fields": {
            "file": {
              "url": "./images/product-1.jpeg"
            }
          }
        }
      }
    },
    {
      "sys": {
        "id": "2"
      },
      "fields": {
        "title": "GIGABYTE WINDFORCE OC",
        "price": 259.99,
        "image": {
          "fields": {
            "file": {
              "url": "./images/product-2.jpeg"
            }
          }
        }
      }
    },
    {
      "sys": {
        "id": "3"
      },
      "fields": {
        "title": "EVGA SC GAMING ACX 3.0 BLACK EDITION",
        "price": 609.00,
        "image": {
          "fields": {
            "file": {
              "url": "./images/product-1.jpeg"
            }
          }
        }
      }
    },
    {
      "sys": {
        "id": "4"
      },
      "fields": {
        "title": "ASUS STRIX GAMING OC",
        "price": 1499.99,
        "image": {
          "fields": {
            "file": {
              "url": "./images/product-2.jpeg"
            }
          }
        }
      }
    },
    {
      "sys": {
        "id": "5"
      },
      "fields": {
        "title": "MSI VENTUS OC",
        "price": 339.99,
        "image": {
          "fields": {
            "file": {
              "url": "./images/product-3.jpeg"
            }
          }
        }
      }
    },
    {
      "sys": {
        "id": "6"
      },
      "fields": {
        "title": "ASUS STRIX GAMMING OC",
        "price": 1899.99,
        "image": {
          "fields": {
            "file": {
              "url": "./images/product-1.jpeg"
            }
          }
        }
      }
    },
    {
      "sys": {
        "id": "7"
      },
      "fields": {
        "title": "GIGABYTE GAMING",
        "price": 449.99,
        "image": {
          "fields": {
            "file": {
              "url": "./images/product-2.jpeg"
            }
          }
        }
      }
    },
    {
      "sys": {
        "id": "8"
      },
      "fields": {
        "title": "NVIDIA FOUNDERS EDITION",
        "price": 699.99,
        "image": {
          "fields": {
            "file": {
              "url": "./images/product-3.jpeg"
            }
          }
        }
      }
    },
    {
      "sys": {
        "id": "9"
      },
      "fields": {
        "title": "NVIDIA FOUNDERS EDITION",
        "price": 526.98,
        "image": {
          "fields": {
            "file": {
              "url": "./images/product-3.jpeg"
            }
          }
        }
      }
    },
    {
      "sys": {
        "id": "10"
      },
      "fields": {
        "title": "SAPPHIRE PULSE",
        "price": 399.99,
        "image": {
          "fields": {
            "file": {
              "url": "./images/product-3.jpeg"
            }
          }
        }
      }
    }
  ]
}